Metadata-Version: 2.1
Name: android-file-bridge
Version: 0.1.1
Summary: Provides easy to use file browser, over ADB
Home-page: https://github.com/valknight/androidfilebridge
Author: Vallerie Knight
Author-email: val@valknight.xyz
License: UNKNOWN
Platform: UNKNOWN
Classifier: Development Status :: 3 - Alpha
Classifier: Programming Language :: Python :: 3
Classifier: License :: Other/Proprietary License
Classifier: Operating System :: MacOS :: MacOS X
Classifier: Operating System :: Microsoft :: Windows
Classifier: Operating System :: POSIX :: Linux
Requires-Python: >=3.6
